pip_and_pip_tools/__init__.py
pip_and_pip_tools-7.5.2.1.dist-info/licenses/LICENSE
pip_and_pip_tools-7.5.2.1.dist-info/WHEEL
pip_and_pip_tools-7.5.2.1.dist-info/METADATA
pip_and_pip_tools-7.5.2.1.dist-info/RECORD
