Metadata-Version: 2.4
Name: pip_and_pip_tools
Version: 7.5.2.1
Summary: Requires compatible installations of pip and pip-tools
Author: Andy Kluger
License-File: LICENSE
Requires-Dist: pip<26
Requires-Dist: pip-tools>=7.5.2
Project-URL: Home, https://github.com/andydecleyre/pip-and-pip-tools
